{
    "domain": "www.democracynow.org",
    "next_page_id": null,
    "url": "http://www.democracynow.org/2013/5/15/headlines/cooper_union_students_continue_tuition_protest",
    "short_url": "http://rdd.me/sgierpzk",
    "author": null,
    "excerpt": "[{\"data-clicky-title\":\"Widget: Find A Topic\",\"link\":\"/topics/2012_election\",\"data-clicky-href\":\"#widget/topics/find\",\"label\":\"2012 Election\"},{\"data-clicky-title\":\"Widget: Find A&hellip;",
    "direction": "ltr",
    "word_count": 1551,
    "total_pages": 0,
    "content": "<div><div class=\"body\">\n      \n\n<p id=\"topics_list\">\n  [{\"data-clicky-title\":\"Widget: Find A Topic\",\"link\":\"/topics/2012_election\",\"data-clicky-href\":\"#widget/topics/find\",\"label\":\"2012 Election\"},{\"data-clicky-title\":\"Widget: Find A Topic\",\"link\":\"/topics/9-11\",\"data-clicky-href\":\"#widget/topics/find\",\"label\":\"9/11\"},{\"data-clicky-title\":\"Widget: Find A Topic\",\"link\":\"/topics/9-11_anniversary\",\"data-clicky-href\":\"#widget/topics/find\",\"label\":\"9/11 anniversary\"},{\"data-clicky-title\":\"Widget: Find A Topic\",\"link\":\"/topics/aaron_swartz\",\"data-clicky-href\":\"#widget/topics/find\",\"label\":\"Aaron Swartz\"},{\"data-clicky-title\":\"Widget: Find A Topic\",\"link\":\"/topics/abortion\",\"data-clicky-href\":\"#widget/topics/find\",\"label\":\"Abortion\"},{\"data-clicky-title\":\"Widget: Find A Topic\",\"link\":\"/topics/academic_freedom\",\"data-clicky-href\":\"#widget/topics/find\",\"label\":\"Academic Freedom\"},{\"data-clicky-title\":\"Widget: Find A Topic\",\"link\":\"/topics/academy_awards\",\"data-clicky-href\":\"#widget/topics/find\",\"label\":\"Academy Awards\"},{\"data-clicky-title\":\"Widget: Find A Topic\",\"link\":\"/topics/aclu\",\"data-clicky-href\":\"#widget/topics/find\",\"label\":\"ACLU\"},{\"data-clicky-title\":\"Widget: Find A Topic\",\"link\":\"/topics/acorn\",\"data-clicky-href\":\"#widget/topics/find\",\"label\":\"ACORN\"},{\"data-clicky-title\":\"Widget: Find A Topic\",\"link\":\"/topics/addiction\",\"data-clicky-href\":\"#widget/topics/find\",\"label\":\"Addiction\"},{\"data-clicky-title\":\"Widget: Find A Topic\",\"link\":\"/topics/afghanistan\",\"data-clicky-href\":\"#widget/topics/find\",\"label\":\"Afghanistan\"},{\"data-clicky-title\":\"Widget: Find A Topic\",\"link\":\"/topics/africa\",\"data-clicky-href\":\"#widget/topics/find\",\"label\":\"Africa\"},{\"data-clicky-title\":\"Widget: Find A Topic\",\"link\":\"/topics/african_american_history\",\"data-clicky-href\":\"#widget/topics/find\",\"label\":\"African-American History\"},{\"data-clicky-title\":\"Widget: Find A Topic\",\"link\":\"/topics/agriculture\",\"data-clicky-href\":\"#widget/topics/find\",\"label\":\"Agriculture\"},{\"data-clicky-title\":\"Widget: Find A Topic\",\"link\":\"/topics/aids\",\"data-clicky-href\":\"#widget/topics/find\",\"label\":\"AIDS\"},{\"data-clicky-title\":\"Widget: Find A Topic\",\"link\":\"/topics/alabama\",\"data-clicky-href\":\"#widget/topics/find\",\"label\":\"Alabama\"},{\"data-clicky-title\":\"Widget: Find A Topic\",\"link\":\"/topics/alec\",\"data-clicky-href\":\"#widget/topics/find\",\"label\":\"ALEC\"},{\"data-clicky-title\":\"Widget: Find A Topic\",\"link\":\"/topics/aminatou_haidar\",\"data-clicky-href\":\"#widget/topics/find\",\"label\":\"Aminatou Haidar\"},{\"data-clicky-title\":\"Widget: Find A Topic\",\"link\":\"/topics/angola_3\",\"data-clicky-href\":\"#widget/topics/find\",\"label\":\"Angola 3\"},{\"data-clicky-title\":\"Widget: Find A Topic\",\"link\":\"/topics/animal_rights\",\"data-clicky-href\":\"#widget/topics/find\",\"label\":\"Animal Rights\"},{\"data-clicky-title\":\"Widget: Find A Topic\",\"link\":\"/topics/anjali_kamat\",\"data-clicky-href\":\"#widget/topics/find\",\"label\":\"Anjali Kamat\"},{\"data-clicky-title\":\"Widget: Find A Topic\",\"link\":\"/topics/anonymous\",\"data-clicky-href\":\"#widget/topics/find\",\"label\":\"Anonymous\"},{\"data-clicky-title\":\"Widget: Find A Topic\",\"link\":\"/topics/anthony_shadid\",\"data-clicky-href\":\"#widget/topics/find\",\"label\":\"Anthony Shadid\"},{\"data-clicky-title\":\"Widget: Find A Topic\",\"link\":\"/topics/arab_spring\",\"data-clicky-href\":\"#widget/topics/find\",\"label\":\"Arab Spring\"},{\"data-clicky-title\":\"Widget: Find A Topic\",\"link\":\"/topics/arabs_and_muslims_in_america\",\"data-clicky-href\":\"#widget/topics/find\",\"label\":\"Arabs and Muslims in America\"},{\"data-clicky-title\":\"Widget: Find A Topic\",\"link\":\"/topics/archive\",\"data-clicky-href\":\"#widget/topics/find\",\"label\":\"Archive\"},{\"data-clicky-title\":\"Widget: Find A Topic\",\"link\":\"/topics/arctic\",\"data-clicky-href\":\"#widget/topics/find\",\"label\":\"Arctic\"},{\"data-clicky-title\":\"Widget: Find A Topic\",\"link\":\"/topics/argentina\",\"data-clicky-href\":\"#widget/topics/find\",\"label\":\"Argentina\"},{\"data-clicky-title\":\"Widget: Find A Topic\",\"link\":\"/topics/arizona\",\"data-clicky-href\":\"#widget/topics/find\",\"label\":\"Arizona\"},{\"data-clicky-title\":\"Widget: Find A Topic\",\"link\":\"/topics/arizona_shooting\",\"data-clicky-href\":\"#widget/topics/find\",\"label\":\"Arizona shooting\"},{\"data-clicky-title\":\"Widget: Find A Topic\",\"link\":\"/topics/arkansas\",\"data-clicky-href\":\"#widget/topics/find\",\"label\":\"Arkansas\"},{\"data-clicky-title\":\"Widget: Find A Topic\",\"link\":\"/topics/arms_trade\",\"data-clicky-href\":\"#widget/topics/find\",\"label\":\"Arms Trade\"},{\"data-clicky-title\":\"Widget: Find A Topic\",\"link\":\"/topics/army\",\"data-clicky-href\":\"#widget/topics/find\",\"label\":\"Army\"},{\"data-clicky-title\":\"Widget: Find A Topic\",\"link\":\"/topics/art_politics\",\"data-clicky-href\":\"#widget/topics/find\",\"label\":\"Art &amp; Politics\"},{\"data-clicky-title\":\"Widget: Find A Topic\",\"link\":\"/topics/asmaa_mahfouz\",\"data-clicky-href\":\"#widget/topics/find\",\"label\":\"Asmaa Mahfouz\"},{\"data-clicky-title\":\"Widget: Find A Topic\",\"link\":\"/topics/atomic\",\"data-clicky-href\":\"#widget/topics/find\",\"label\":\"Atomic\"},{\"data-clicky-title\":\"Widget: Find A Topic\",\"link\":\"/topics/atomic_bomb\",\"data-clicky-href\":\"#widget/topics/find\",\"label\":\"Atomic Bomb\"},{\"data-clicky-title\":\"Widget: Find A Topic\",\"link\":\"/topics/aurora_shooting\",\"data-clicky-href\":\"#widget/topics/find\",\"label\":\"Aurora Shooting\"},{\"data-clicky-title\":\"Widget: Find A Topic\",\"link\":\"/topics/author_interviews\",\"data-clicky-href\":\"#widget/topics/find\",\"label\":\"Author Interviews\"},{\"data-clicky-title\":\"Widget: Find A Topic\",\"link\":\"/topics/bahrain\",\"data-clicky-href\":\"#widget/topics/find\",\"label\":\"Bahrain\"},{\"data-clicky-title\":\"Widget: Find A Topic\",\"link\":\"/topics/bainport\",\"data-clicky-href\":\"#widget/topics/find\",\"label\":\"Bainport\"},{\"data-clicky-title\":\"Widget: Find A Topic\",\"link\":\"/topics/bangladesh\",\"data-clicky-href\":\"#widget/topics/find\",\"label\":\"Bangladesh\"},{\"data-clicky-title\":\"Widget: Find A Topic\",\"link\":\"/topics/barbara_ehrenreich\",\"data-clicky-href\":\"#widget/topics/find\",\"label\":\"Barbara Ehrenreich\"},{\"data-clicky-title\":\"Widget: Find A Topic\",\"link\":\"/topics/bart\",\"data-clicky-href\":\"#widget/topics/find\",\"label\":\"BART\"},{\"data-clicky-title\":\"Widget: Find A Topic\",\"link\":\"/topics/bhopal_disaster\",\"data-clicky-href\":\"#widget/topics/find\",\"label\":\"Bhopal disaster\"},{\"data-clicky-title\":\"Widget: Find A Topic\",\"link\":\"/topics/birth_control\",\"data-clicky-href\":\"#widget/topics/find\",\"label\":\"Birth Control\"},{\"data-clicky-title\":\"Widget: Find A Topic\",\"link\":\"/topics/black_panthers\",\"data-clicky-href\":\"#widget/topics/find\",\"label\":\"Black Panthers\"},{\"data-clicky-title\":\"Widget: Find A Topic\",\"link\":\"/topics/blackwater\",\"data-clicky-href\":\"#widget/topics/find\",\"label\":\"Blackwater\"},{\"data-clicky-title\":\"Widget: Find A Topic\",\"link\":\"/topics/bolivia\",\"data-clicky-href\":\"#widget/topics/find\",\"label\":\"Bolivia\"},{\"data-clicky-title\":\"Widget: Find A Topic\",\"link\":\"/topics/books\",\"data-clicky-href\":\"#widget/topics/find\",\"label\":\"Books\"},{\"data-clicky-title\":\"Widget: Find A Topic\",\"link\":\"/topics/border_patrol\",\"data-clicky-href\":\"#widget/topics/find\",\"label\":\"Border Patrol\"},{\"data-clicky-title\":\"Widget: Find A Topic\",\"link\":\"/topics/boston_marathon_bombing\",\"data-clicky-href\":\"#widget/topics/find\",\"label\":\"Boston Marathon Bombing\"},{\"data-clicky-title\":\"Widget: Find A Topic\",\"link\":\"/topics/bp_oil_spill\",\"data-clicky-href\":\"#widget/topics/find\",\"label\":\"BP Oil Spill\"},{\"data-clicky-title\":\"Widget: Find A Topic\",\"link\":\"/topics/bradley_manning\",\"data-clicky-href\":\"#widget/topics/find\",\"label\":\"Bradley Manning\"},{\"data-clicky-title\":\"Widget: Find A Topic\",\"link\":\"/topics/britain\",\"data-clicky-href\":\"#widget/topics/find\",\"label\":\"Britain\"},{\"data-clicky-title\":\"Widget: Find A Topic\",\"link\":\"/topics/burma\",\"data-clicky-href\":\"#widget/topics/find\",\"label\":\"Burma\"},{\"data-clicky-title\":\"Widget: Find A Topic\",\"link\":\"/topics/bush\",\"data-clicky-href\":\"#widget/topics/find\",\"label\":\"Bush\"},{\"data-clicky-title\":\"Widget: Find A Topic\",\"link\":\"/topics/cafta\",\"data-clicky-href\":\"#widget/topics/find\",\"label\":\"CAFTA\"},{\"data-clicky-title\":\"Widget: Find A Topic\",\"link\":\"/topics/california\",\"data-clicky-href\":\"#widget/topics/find\",\"label\":\"California\"},{\"data-clicky-title\":\"Widget: Find A Topic\",\"link\":\"/topics/campaign_finance\",\"data-clicky-href\":\"#widget/topics/find\",\"label\":\"campaign finance\"},{\"data-clicky-title\":\"Widget: Find A Topic\",\"link\":\"/topics/canada\",\"data-clicky-href\":\"#widget/topics/find\",\"label\":\"Canada\"},{\"data-clicky-title\":\"Widget: Find A Topic\",\"link\":\"/topics/cancn_climate_summit\",\"data-clicky-href\":\"#widget/topics/find\",\"label\":\"Canc\\u00fan Climate Summit\"},{\"data-clicky-title\":\"Widget: Find A Topic\",\"link\":\"/topics/catholic_church\",\"data-clicky-href\":\"#widget/topics/find\",\"label\":\"Catholic Church\"},{\"data-clicky-title\":\"Widget: Find A Topic\",\"link\":\"/topics/central_park_five\",\"data-clicky-href\":\"#widget/topics/find\",\"label\":\"Central Park Five\"},{\"data-clicky-title\":\"Widget: Find A Topic\",\"link\":\"/topics/chalmers_johnson\",\"data-clicky-href\":\"#widget/topics/find\",\"label\":\"Chalmers Johnson\"},{\"data-clicky-title\":\"Widget: Find A Topic\",\"link\":\"/topics/charter_schools\",\"data-clicky-href\":\"#widget/topics/find\",\"label\":\"Charter Schools\"},{\"data-clicky-title\":\"Widget: Find A Topic\",\"link\":\"/topics/chicago\",\"data-clicky-href\":\"#widget/topics/find\",\"label\":\"Chicago\"},{\"data-clicky-title\":\"Widget: Find A Topic\",\"link\":\"/topics/chile\",\"data-clicky-href\":\"#widget/topics/find\",\"label\":\"Chile\"},{\"data-clicky-title\":\"Widget: Find A Topic\",\"link\":\"/topics/china\",\"data-clicky-href\":\"#widget/topics/find\",\"label\":\"China\"},{\"data-clicky-title\":\"Widget: Find A Topic\",\"link\":\"/topics/citizens_united\",\"data-clicky-href\":\"#widget/topics/find\",\"label\":\"Citizens United\"},{\"data-clicky-title\":\"Widget: Find A Topic\",\"link\":\"/topics/civil_rights\",\"data-clicky-href\":\"#widget/topics/find\",\"label\":\"Civil Rights\"},{\"data-clicky-title\":\"Widget: Find A Topic\",\"link\":\"/topics/climate_change\",\"data-clicky-href\":\"#widget/topics/find\",\"label\":\"Climate Change\"},{\"data-clicky-title\":\"Widget: Find A Topic\",\"link\":\"/topics/cmus\",\"data-clicky-href\":\"#widget/topics/find\",\"label\":\"CMUs\"},{\"data-clicky-title\":\"Widget: Find A Topic\",\"link\":\"/topics/coal\",\"data-clicky-href\":\"#widget/topics/find\",\"label\":\"Coal\"},{\"data-clicky-title\":\"Widget: Find A Topic\",\"link\":\"/topics/cointelpro\",\"data-clicky-href\":\"#widget/topics/find\",\"label\":\"COINTELPRO\"},{\"data-clicky-title\":\"Widget: Find A Topic\",\"link\":\"/topics/colombia\",\"data-clicky-href\":\"#widget/topics/find\",\"label\":\"Colombia\"},{\"data-clicky-title\":\"Widget: Find A Topic\",\"link\":\"/topics/colorado\",\"data-clicky-href\":\"#widget/topics/find\",\"label\":\"Colorado\"},{\"data-clicky-title\":\"Widget: Find A Topic\",\"link\":\"/topics/columbus_day\",\"data-clicky-href\":\"#widget/topics/find\",\"label\":\"Columbus Day\"},{\"data-clicky-title\":\"Widget: Find A Topic\",\"link\":\"/topics/congo\",\"data-clicky-href\":\"#widget/topics/find\",\"label\":\"Congo\"},{\"data-clicky-title\":\"Widget: Find A Topic\",\"link\":\"/topics/connecticut\",\"data-clicky-href\":\"#widget/topics/find\",\"label\":\"Connecticut\"},{\"data-clicky-title\":\"Widget: Find A Topic\",\"link\":\"/topics/copenhagen_climate_summit\",\"data-clicky-href\":\"#widget/topics/find\",\"label\":\"Copenhagen Climate Summit 2009\"},{\"data-clicky-title\":\"Widget: Find A Topic\",\"link\":\"/topics/cornel_west\",\"data-clicky-href\":\"#widget/topics/find\",\"label\":\"Cornel West\"},{\"data-clicky-title\":\"Widget: Find A Topic\",\"link\":\"/topics/corporate_power\",\"data-clicky-href\":\"#widget/topics/find\",\"label\":\"Corporate Power\"},{\"data-clicky-title\":\"Widget: Find A Topic\",\"link\":\"/topics/cuba\",\"data-clicky-href\":\"#widget/topics/find\",\"label\":\"Cuba\"},{\"data-clicky-title\":\"Widget: Find A Topic\",\"link\":\"/topics/cyprus\",\"data-clicky-href\":\"#widget/topics/find\",\"label\":\"Cyprus\"},{\"data-clicky-title\":\"Widget: Find A Topic\",\"link\":\"/topics/dadt\",\"data-clicky-href\":\"#widget/topics/find\",\"label\":\"DADT\"},{\"data-clicky-title\":\"Widget: Find A Topic\",\"link\":\"/topics/dalai_lama\",\"data-clicky-href\":\"#widget/topics/find\",\"label\":\"Dalai Lama\"},{\"data-clicky-title\":\"Widget: Find A Topic\",\"link\":\"/topics/danny_chen\",\"data-clicky-href\":\"#widget/topics/find\",\"label\":\"Danny Chen\"},{\"data-clicky-title\":\"Widget: Find A Topic\",\"link\":\"/topics/danziger_bridge\",\"data-clicky-href\":\"#widget/topics/find\",\"label\":\"Danziger Bridge\"},{\"data-clicky-title\":\"Widget: Find A Topic\",\"link\":\"/topics/david_cay_johnston\",\"data-clicky-href\":\"#widget/topics/find\",\"label\":\"David Cay Johnston\"},{\"data-clicky-title\":\"Widget: Find A Topic\",\"link\":\"/topics/death_penalty\",\"data-clicky-href\":\"#widget/topics/find\",\"label\":\"Death Penalty\"},{\"data-clicky-title\":\"Widget: Find A Topic\",\"link\":\"/topics/debt\",\"data-clicky-href\":\"#widget/topics/find\",\"label\":\"Debt\"},{\"data-clicky-title\":\"Widget: Find A Topic\",\"link\":\"/topics/deficit\",\"data-clicky-href\":\"#widget/topics/find\",\"label\":\"Deficit\"},{\"data-clicky-title\":\"Widget: Find A Topic\",\"link\":\"/topics/democracy\",\"data-clicky-href\":\"#widget/topics/find\",\"label\":\"democracy\"},{\"data-clicky-title\":\"Widget: Find A Topic\",\"link\":\"/topics/democratic_party\",\"data-clicky-href\":\"#widget/topics/find\",\"label\":\"Democratic Party\"},{\"data-clicky-title\":\"Widget: Find A Topic\",\"link\":\"/topics/dennis_brutus\",\"data-clicky-href\":\"#widget/topics/find\",\"label\":\"Dennis Brutus\"},{\"data-clicky-title\":\"Widget: Find A Topic\",\"link\":\"/topics/detroit\",\"data-clicky-href\":\"#widget/topics/find\",\"label\":\"Detroit\"},{\"data-clicky-title\":\"Widget: Find A Topic\",\"link\":\"/topics/dick_cheney\",\"data-clicky-href\":\"#widget/topics/find\",\"label\":\"Dick Cheney\"},{\"data-clicky-title\":\"Widget: Find A Topic\",\"link\":\"/topics/dixie_chicks\",\"data-clicky-href\":\"#widget/topics/find\",\"label\":\"Dixie Chicks\"},{\"data-clicky-title\":\"Widget: Find A Topic\",\"link\":\"/topics/dnc_2012\",\"data-clicky-href\":\"#widget/topics/find\",\"label\":\"DNC 2012\"},{\"data-clicky-title\":\"Widget: Find A Topic\",\"link\":\"/topics/qatar_climate_summit_2012\",\"data-clicky-href\":\"#widget/topics/find\",\"label\":\"Doha Climate Summit 2012\"},{\"data-clicky-title\":\"Widget: Find A Topic\",\"link\":\"/topics/domestic_spying\",\"data-clicky-href\":\"#widget/topics/find\",\"label\":\"Domestic Spying\"},{\"data-clicky-title\":\"Widget: Find A Topic\",\"link\":\"/topics/domestic_surveillance\",\"data-clicky-href\":\"#widget/topics/find\",\"label\":\"Domestic Surveillance\"},{\"data-clicky-title\":\"Widget: Find A Topic\",\"link\":\"/topics/domestic_violence\",\"data-clicky-href\":\"#widget/topics/find\",\"label\":\"Domestic Violence\"},{\"data-clicky-title\":\"Widget: Find A Topic\",\"link\":\"/topics/dont_ask_dont_tell\",\"data-clicky-href\":\"#widget/topics/find\",\"label\":\"Don't Ask Don't Tell Policy\"},{\"data-clicky-title\":\"Widget: Find A Topic\",\"link\":\"/topics/donald_rumsfeld\",\"data-clicky-href\":\"#widget/topics/find\",\"label\":\"Donald Rumsfeld\"},{\"data-clicky-title\":\"Widget: Find A Topic\",\"link\":\"/topics/dream_act\",\"data-clicky-href\":\"#widget/topics/find\",\"label\":\"DREAM Act\"},{\"data-clicky-title\":\"Widget: Find A Topic\",\"link\":\"/topics/drone_attacks\",\"data-clicky-href\":\"#widget/topics/find\",\"label\":\"Drone Attacks\"},{\"data-clicky-title\":\"Widget: Find A Topic\",\"link\":\"/topics/drones\",\"data-clicky-href\":\"#widget/topics/find\",\"label\":\"Drones\"},{\"data-clicky-title\":\"Widget: Find A Topic\",\"link\":\"/topics/drug_war\",\"data-clicky-href\":\"#widget/topics/find\",\"label\":\"Drug War\"},{\"data-clicky-title\":\"Widget: Find A Topic\",\"link\":\"/topics/durban_climate_summit_2011\",\"data-clicky-href\":\"#widget/topics/find\",\"label\":\"Durban Climate Summit 2011\"},{\"data-clicky-title\":\"Widget: Find A Topic\",\"link\":\"/topics/earth_day\",\"data-clicky-href\":\"#widget/topics/find\",\"label\":\"Earth Day\"},{\"data-clicky-title\":\"Widget: Find A Topic\",\"link\":\"/topics/east_timor\",\"data-clicky-href\":\"#widget/topics/find\",\"label\":\"East Timor\"},{\"data-clicky-title\":\"Widget: Find A Topic\",\"link\":\"/topics/economy\",\"data-clicky-href\":\"#widget/topics/find\",\"label\":\"Economy\"},{\"data-clicky-title\":\"Widget: Find A Topic\",\"link\":\"/topics/ecuador\",\"data-clicky-href\":\"#widget/topics/find\",\"label\":\"Ecuador\"},{\"data-clicky-title\":\"Widget: Find A Topic\",\"link\":\"/topics/eddie_vedder\",\"data-clicky-href\":\"#widget/topics/find\",\"label\":\"Eddie Vedder\"},{\"data-clicky-title\":\"Widget: Find A Topic\",\"link\":\"/topics/education\",\"data-clicky-href\":\"#widget/topics/find\",\"label\":\"Education\"},{\"data-clicky-title\":\"Widget: Find A Topic\",\"link\":\"/topics/egypt\",\"data-clicky-href\":\"#widget/topics/find\",\"label\":\"Egypt\"},{\"data-clicky-title\":\"Widget: Find A Topic\",\"link\":\"/topics/el_nino\",\"data-clicky-href\":\"#widget/topics/find\",\"label\":\"El Nino\"},{\"data-clicky-title\":\"Widget: Find A Topic\",\"link\":\"/topics/el_salvador\",\"data-clicky-href\":\"#widget/topics/find\",\"label\":\"El Salvador\"},{\"data-clicky-title\":\"Widget: Find A Topic\",\"link\":\"/topics/election_2012\",\"data-clicky-href\":\"#widget/topics/find\",\"label\":\"Election 2012\"},{\"data-clicky-title\":\"Widget: Find A Topic\",\"link\":\"/topics/elections_2010\",\"data-clicky-href\":\"#widget/topics/find\",\"label\":\"Elections 2010\"},{\"data-clicky-title\":\"Widget: Find A Topic\",\"link\":\"/topics/elena_kagan\",\"data-clicky-href\":\"#widget/topics/find\",\"label\":\"Elena Kagan\"},{\"data-clicky-title\":\"Widget: Find A Topic\",\"link\":\"/topics/environment\",\"data-clicky-href\":\"#widget/topics/find\",\"label\":\"Environment\"},{\"data-clicky-title\":\"Widget: Find A Topic\",\"link\":\"/topics/ethiopia\",\"data-clicky-href\":\"#widget/topics/find\",\"label\":\"Ethiopia\"},{\"data-clicky-title\":\"Widget: Find A Topic\",\"link\":\"/topics/eve_ensler\",\"data-clicky-href\":\"#widget/topics/find\",\"label\":\"Eve Ensler\"},{\"data-clicky-title\":\"Widget: Find A Topic\",\"link\":\"/topics/expanding_the_debate\",\"data-clicky-href\":\"#widget/topics/find\",\"label\":\"Expanding The Debate\"},{\"data-clicky-title\":\"Widget: Find A Topic\",\"link\":\"/topics/extreme_weather\",\"data-clicky-href\":\"#widget/topics/find\",\"label\":\"extreme weather\"},{\"data-clicky-title\":\"Widget: Find A Topic\",\"link\":\"/topics/exxon_valdez_disaster\",\"data-clicky-href\":\"#widget/topics/find\",\"label\":\"Exxon Valdez Disaster\"},{\"data-clicky-title\":\"Widget: Find A Topic\",\"link\":\"/topics/famine\",\"data-clicky-href\":\"#widget/topics/find\",\"label\":\"Famine\"},{\"data-clicky-title\":\"Widget: Find A Topic\",\"link\":\"/topics/fbi\",\"data-clicky-href\":\"#widget/topics/find\",\"label\":\"FBI\"},{\"data-clicky-title\":\"Widget: Find A Topic\",\"link\":\"/topics/fcc\",\"data-clicky-href\":\"#widget/topics/find\",\"label\":\"FCC\"},{\"data-clicky-title\":\"Widget: Find A Topic\",\"link\":\"/topics/fda\",\"data-clicky-href\":\"#widget/topics/find\",\"label\":\"FDA\"},{\"data-clicky-title\":\"Widget: Find A Topic\",\"link\":\"/topics/film\",\"data-clicky-href\":\"#widget/topics/find\",\"label\":\"Film\"},{\"data-clicky-title\":\"Widget: Find A Topic\",\"link\":\"/topics/financial_meltdown\",\"data-clicky-href\":\"#widget/topics/find\",\"label\":\"Financial Meltdown\"},{\"data-clicky-title\":\"Widget: Find A Topic\",\"link\":\"/topics/florida\",\"data-clicky-href\":\"#widget/topics/find\",\"label\":\"Florida\"},{\"data-clicky-title\":\"Widget: Find A Topic\",\"link\":\"/topics/food\",\"data-clicky-href\":\"#widget/topics/find\",\"label\":\"Food\"},{\"data-clicky-title\":\"Widget: Find A Topic\",\"link\":\"/topics/food_stamps\",\"data-clicky-href\":\"#widget/topics/find\",\"label\":\"Food stamps\"},{\"data-clicky-title\":\"Widget: Find A Topic\",\"link\":\"/topics/foodstamps\",\"data-clicky-href\":\"#widget/topics/find\",\"label\":\"foodstamps\"},{\"data-clicky-title\":\"Widget: Find A Topic\",\"link\":\"/topics/france\",\"data-clicky-href\":\"#widget/topics/find\",\"label\":\"France\"},{\"data-clicky-title\":\"Widget: Find A Topic\",\"link\":\"/topics/freedom_of_the_press\",\"data-clicky-href\":\"#widget/topics/find\",\"label\":\"Freedom of the Press\"},{\"data-clicky-title\":\"Widget: Find A Topic\",\"link\":\"/topics/fukushima\",\"data-clicky-href\":\"#widget/topics/find\",\"label\":\"Fukushima\"},{\"data-clicky-title\":\"Widget: Find A Topic\",\"link\":\"/topics/gabor_mat\",\"data-clicky-href\":\"#widget/topics/find\",\"label\":\"Gabor Mat\\u00e9\"},{\"data-clicky-title\":\"Widget: Find A Topic\",\"link\":\"/topics/gay_marriage\",\"data-clicky-href\":\"#widget/topics/find\",\"label\":\"Gay marriage\"},{\"data-clicky-title\":\"Widget: Find A Topic\",\"link\":\"/topics/gay_rights\",\"data-clicky-href\":\"#widget/topics/find\",\"label\":\"Gay Rights\"},{\"data-clicky-title\":\"Widget: Find A Topic\",\"link\":\"/topics/gaza\",\"data-clicky-href\":\"#widget/topics/find\",\"label\":\"Gaza\"},{\"data-clicky-title\":\"Widget: Find A Topic\",\"link\":\"/topics/flotilla\",\"data-clicky-href\":\"#widget/topics/find\",\"label\":\"Gaza Flotilla\"},{\"data-clicky-title\":\"Widget: Find A Topic\",\"link\":\"/topics/george_weller\",\"data-clicky-href\":\"#widget/topics/find\",\"label\":\"George Weller\"},{\"data-clicky-title\":\"Widget: Find A Topic\",\"link\":\"/topics/georgia\",\"data-clicky-href\":\"#widget/topics/find\",\"label\":\"Georgia\"},{\"data-clicky-title\":\"Widget: Find A Topic\",\"link\":\"/topics/glenn_greenwald\",\"data-clicky-href\":\"#widget/topics/find\",\"label\":\"Glenn Greenwald\"},{\"data-clicky-title\":\"Widget: Find A Topic\",\"link\":\"/topics/global_warming\",\"data-clicky-href\":\"#widget/topics/find\",\"label\":\"Global Warming\"},{\"data-clicky-title\":\"Widget: Find A Topic\",\"link\":\"/topics/global_warrming\",\"data-clicky-href\":\"#widget/topics/find\",\"label\":\"Global Warrming\"},{\"data-clicky-title\":\"Widget: Find A Topic\",\"link\":\"/topics/goldman_sachs\",\"data-clicky-href\":\"#widget/topics/find\",\"label\":\"Goldman Sachs\"},{\"data-clicky-title\":\"Widget: Find A Topic\",\"link\":\"/topics/goldstone\",\"data-clicky-href\":\"#widget/topics/find\",\"label\":\"Goldstone\"},{\"data-clicky-title\":\"Widget: Find A Topic\",\"link\":\"/topics/greece\",\"data-clicky-href\":\"#widget/topics/find\",\"label\":\"Greece\"},{\"data-clicky-title\":\"Widget: Find A Topic\",\"link\":\"/topics/green_party\",\"data-clicky-href\":\"#widget/topics/find\",\"label\":\"Green Party\"},{\"data-clicky-title\":\"Widget: Find A Topic\",\"link\":\"/topics/green_scare\",\"data-clicky-href\":\"#widget/topics/find\",\"label\":\"Green scare\"},{\"data-clicky-title\":\"Widget: Find A Topic\",\"link\":\"/topics/green_zone\",\"data-clicky-href\":\"#widget/topics/find\",\"label\":\"Green Zone\"},{\"data-clicky-title\":\"Widget: Find A Topic\",\"link\":\"/topics/ground_zero_workers\",\"data-clicky-href\":\"#widget/topics/find\",\"label\":\"Ground Zero workers\"},{\"data-clicky-title\":\"Widget: Find A Topic\",\"link\":\"/topics/guantanamo\",\"data-clicky-href\":\"#widget/topics/find\",\"label\":\"Guantanamo\"},{\"data-clicky-title\":\"Widget: Find A Topic\",\"link\":\"/topics/guatemala\",\"data-clicky-href\":\"#widget/topics/find\",\"label\":\"Guatemala\"},{\"data-clicky-title\":\"Widget: Find A Topic\",\"link\":\"/topics/gun_control\",\"data-clicky-href\":\"#widget/topics/find\",\"label\":\"Gun Control\"},{\"data-clicky-title\":\"Widget: Find A Topic\",\"link\":\"/topics/hacking\",\"data-clicky-href\":\"#widget/topics/find\",\"label\":\"Hacking\"},{\"data-clicky-title\":\"Widget: Find A Topic\",\"link\":\"/topics/hacktivism\",\"data-clicky-href\":\"#widget/topics/find\",\"label\":\"Hacktivism\"},{\"data-clicky-title\":\"Widget: Find A Topic\",\"link\":\"/topics/haiti\",\"data-clicky-href\":\"#widget/topics/find\",\"label\":\"Haiti\"},{\"data-clicky-title\":\"Widget: Find A Topic\",\"link\":\"/topics/haiti_earthquake\",\"data-clicky-href\":\"#widget/topics/find\",\"label\":\"Haiti Earthquake\"},{\"data-clicky-title\":\"Widget: Find A Topic\",\"link\":\"/topics/hamas\",\"data-clicky-href\":\"#widget/topics/find\",\"label\":\"Hamas\"},{\"data-clicky-title\":\"Widget: Find A Topic\",\"link\":\"/topics/harry_belafonte\",\"data-clicky-href\":\"#widget/topics/find\",\"label\":\"Harry Belafonte\"},{\"data-clicky-title\":\"Widget: Find A Topic\",\"link\":\"/topics/healthcare\",\"data-clicky-href\":\"#widget/topics/find\",\"label\":\"Healthcare\"},{\"data-clicky-title\":\"Widget: Find A Topic\",\"link\":\"/topics/hiroshima\",\"data-clicky-href\":\"#widget/topics/find\",\"label\":\"Hiroshima\"},{\"data-clicky-title\":\"Widget: Find A Topic\",\"link\":\"/topics/hiroshima_nagasaki\",\"data-clicky-href\":\"#widget/topics/find\",\"label\":\"Hiroshima Nagasaki\"},{\"data-clicky-title\":\"Widget: Find A Topic\",\"link\":\"/topics/hiv\",\"data-clicky-href\":\"#widget/topics/find\",\"label\":\"HIV\"},{\"data-clicky-title\":\"Widget: Find A Topic\",\"link\":\"/topics/honduras\",\"data-clicky-href\":\"#widget/topics/find\",\"label\":\"Honduras\"},{\"data-clicky-title\":\"Widget: Find A Topic\",\"link\":\"/topics/howard_zinn\",\"data-clicky-href\":\"#widget/topics/find\",\"label\":\"Howard Zinn Interviews\"},{\"data-clicky-title\":\"Widget: Find A Topic\",\"link\":\"/topics/hugo_chavez\",\"data-clicky-href\":\"#widget/topics/find\",\"label\":\"Hugo Chavez\"},{\"data-clicky-title\":\"Widget: Find A Topic\",\"link\":\"/topics/human_rights\",\"data-clicky-href\":\"#widget/topics/find\",\"label\":\"Human Rights\"},{\"data-clicky-title\":\"Widget: Find A Topic\",\"link\":\"/topics/hunger_strike\",\"data-clicky-href\":\"#widget/topics/find\",\"label\":\"Hunger Strike\"},{\"data-clicky-title\":\"Widget: Find A Topic\",\"link\":\"/topics/hurricane\",\"data-clicky-href\":\"#widget/topics/find\",\"label\":\"Hurricane\"},{\"data-clicky-title\":\"Widget: Find A Topic\",\"link\":\"/topics/hurricane_katrina\",\"data-clicky-href\":\"#widget/topics/find\",\"label\":\"Hurricane Katrina\"},{\"data-clicky-title\":\"Widget: Find A Topic\",\"link\":\"/topics/hurricane_sandy\",\"data-clicky-href\":\"#widget/topics/find\",\"label\":\"Hurricane Sandy\"},{\"data-clicky-title\":\"Widget: Find A Topic\",\"link\":\"/topics/idaho\",\"data-clicky-href\":\"#widget/topics/find\",\"label\":\"Idaho\"},{\"data-clicky-title\":\"Widget: Find A Topic\",\"link\":\"/topics/idle_no_more\",\"data-clicky-href\":\"#widget/topics/find\",\"label\":\"Idle No More\"},{\"data-clicky-title\":\"Widget: Find A Topic\",\"link\":\"/topics/illinois\",\"data-clicky-href\":\"#widget/topics/find\",\"label\":\"Illinois\"},{\"data-clicky-title\":\"Widget: Find A Topic\",\"link\":\"/topics/immigrant_rights\",\"data-clicky-href\":\"#widget/topics/find\",\"label\":\"Immigrant Rights\"},{\"data-clicky-title\":\"Widget: Find A Topic\",\"link\":\"/topics/immigration\",\"data-clicky-href\":\"#widget/topics/find\",\"label\":\"Immigration\"},{\"data-clicky-title\":\"Widget: Find A Topic\",\"link\":\"/topics/india\",\"data-clicky-href\":\"#widget/topics/find\",\"label\":\"India\"},{\"data-clicky-title\":\"Widget: Find A Topic\",\"link\":\"/topics/indiana\",\"data-clicky-href\":\"#widget/topics/find\",\"label\":\"Indiana\"},{\"data-clicky-title\":\"Widget: Find A Topic\",\"link\":\"/topics/indigenous\",\"data-clicky-href\":\"#widget/topics/find\",\"label\":\"Indigenous\"},{\"data-clicky-title\":\"Widget: Find A Topic\",\"link\":\"/topics/indonesia\",\"data-clicky-href\":\"#widget/topics/find\",\"label\":\"Indonesia\"},{\"data-clicky-title\":\"Widget: Find A Topic\",\"link\":\"/topics/internet\",\"data-clicky-href\":\"#widget/topics/find\",\"label\":\"Internet\"},{\"data-clicky-title\":\"Widget: Find A Topic\",\"link\":\"/topics/iowa\",\"data-clicky-href\":\"#widget/topics/find\",\"label\":\"Iowa\"},{\"data-clicky-title\":\"Widget: Find A Topic\",\"link\":\"/topics/iran\",\"data-clicky-href\":\"#widget/topics/find\",\"label\":\"Iran\"},{\"data-clicky-title\":\"Widget: Find A Topic\",\"link\":\"/topics/iraq\",\"data-clicky-href\":\"#widget/topics/find\",\"label\":\"Iraq\"},{\"data-clicky-title\":\"Widget: Find A Topic\",\"link\":\"/topics/islam\",\"data-clicky-href\":\"#widget/topics/find\",\"label\":\"Islam\"},{\"data-clicky-title\":\"Widget: Find A Topic\",\"link\":\"/topics/israel\",\"data-clicky-href\":\"#widget/topics/find\",\"label\":\"Israel\"},{\"data-clicky-title\":\"Widget: Find A Topic\",\"link\":\"/topics/israel_and_palestine\",\"data-clicky-href\":\"#widget/topics/find\",\"label\":\"Israel &amp; Palestine\"},{\"data-clicky-title\":\"Widget: Find A Topic\",\"link\":\"/topics/italy\",\"data-clicky-href\":\"#widget/topics/find\",\"label\":\"Italy\"},{\"data-clicky-title\":\"Widget: Find A Topic\",\"link\":\"/topics/japan\",\"data-clicky-href\":\"#widget/topics/find\",\"label\":\"Japan\"},{\"data-clicky-title\":\"Widget: Find A Topic\",\"link\":\"/topics/japan_disaster\",\"data-clicky-href\":\"#widget/topics/find\",\"label\":\"Japan Disaster\"},{\"data-clicky-title\":\"Widget: Find A Topic\",\"link\":\"/topics/jean_bertrand_aristide\",\"data-clicky-href\":\"#widget/topics/find\",\"label\":\"Jean-Bertrand Aristide\"},{\"data-clicky-title\":\"Widget: Find A Topic\",\"link\":\"/topics/jeff_luers\",\"data-clicky-href\":\"#widget/topics/find\",\"label\":\"Jeff \\\"Free\\\" Luers\"},{\"data-clicky-title\":\"Widget: Find A Topic\",\"link\":\"/topics/jeff_biggers\",\"data-clicky-href\":\"#widget/topics/find\",\"label\":\"Jeff Biggers\"},{\"data-clicky-title\":\"Widget: Find A Topic\",\"link\":\"/topics/jeremy_scahill\",\"data-clicky-href\":\"#widget/topics/find\",\"label\":\"Jeremy Scahill\"},{\"data-clicky-title\":\"Widget: Find A Topic\",\"link\":\"/topics/john_brennan\",\"data-clicky-href\":\"#widget/topics/find\",\"label\":\"John Brennan\"},{\"data-clicky-title\":\"Widget: Find A Topic\",\"link\":\"/topics/john_walker_lindh\",\"data-clicky-href\":\"#widget/topics/find\",\"label\":\"John Walker Lindh\"},{\"data-clicky-title\":\"Widget: Find A Topic\",\"link\":\"/topics/journalism\",\"data-clicky-href\":\"#widget/topics/find\",\"label\":\"journalism\"},{\"data-clicky-title\":\"Widget: Find A Topic\",\"link\":\"/topics/juan_cole\",\"data-clicky-href\":\"#widget/topics/find\",\"label\":\"Juan Cole\"},{\"data-clicky-title\":\"Widget: Find A Topic\",\"link\":\"/topics/juan_gonzalez\",\"data-clicky-href\":\"#widget/topics/find\",\"label\":\"Juan Gonzalez\"},{\"data-clicky-title\":\"Widget: Find A Topic\",\"link\":\"/topics/juan_manuel_garca_passalacqua\",\"data-clicky-href\":\"#widget/topics/find\",\"label\":\"Juan Manuel Garc\\u00eda-Passalacqua\"},{\"data-clicky-title\":\"Widget: Find A Topic\",\"link\":\"/topics/julian_assange\",\"data-clicky-href\":\"#widget/topics/find\",\"label\":\"Julian Assange\"},{\"data-clicky-title\":\"Widget: Find A Topic\",\"link\":\"/topics/karl_rove\",\"data-clicky-href\":\"#widget/topics/find\",\"label\":\"Karl Rove\"},{\"data-clicky-title\":\"Widget: Find A Topic\",\"link\":\"/topics/kashmir\",\"data-clicky-href\":\"#widget/topics/find\",\"label\":\"Kashmir\"},{\"data-clicky-title\":\"Widget: Find A Topic\",\"link\":\"/topics/kenneth_chamberlain\",\"data-clicky-href\":\"#widget/topics/find\",\"label\":\"Kenneth Chamberlain\"},{\"data-clicky-title\":\"Widget: Find A Topic\",\"link\":\"/topics/keystone_xl\",\"data-clicky-href\":\"#widget/topics/find\",\"label\":\"Keystone XL\"},{\"data-clicky-title\":\"Widget: Find A Topic\",\"link\":\"/topics/koch_brothers\",\"data-clicky-href\":\"#widget/topics/find\",\"label\":\"Koch Brothers\"},{\"data-clicky-title\":\"Widget: Find A Topic\",\"link\":\"/topics/labor\",\"data-clicky-href\":\"#widget/topics/find\",\"label\":\"Labor\"},{\"data-clicky-title\":\"Widget: Find A Topic\",\"link\":\"/topics/laos\",\"data-clicky-href\":\"#widget/topics/find\",\"label\":\"Laos\"},{\"data-clicky-title\":\"Widget: Find A Topic\",\"link\":\"/topics/latin_america\",\"data-clicky-href\":\"#widget/topics/find\",\"label\":\"Latin America\"},{\"data-clicky-title\":\"Widget: Find A Topic\",\"link\":\"/topics/legistlation\",\"data-clicky-href\":\"#widget/topics/find\",\"label\":\"legistlation\"},{\"data-clicky-title\":\"Widget: Find A Topic\",\"link\":\"/topics/leonard_peltier\",\"data-clicky-href\":\"#widget/topics/find\",\"label\":\"Leonard Peltier\"},{\"data-clicky-title\":\"Widget: Find A Topic\",\"link\":\"/topics/lgbt\",\"data-clicky-href\":\"#widget/topics/find\",\"label\":\"LGBT\"},{\"data-clicky-title\":\"Widget: Find A Topic\",\"link\":\"/topics/liberia\",\"data-clicky-href\":\"#widget/topics/find\",\"label\":\"Liberia\"},{\"data-clicky-title\":\"Widget: Find A Topic\",\"link\":\"/topics/library\",\"data-clicky-href\":\"#widget/topics/find\",\"label\":\"Library\"},{\"data-clicky-title\":\"Widget: Find A Topic\",\"link\":\"/topics/libya\",\"data-clicky-href\":\"#widget/topics/find\",\"label\":\"Libya\"},{\"data-clicky-title\":\"Widget: Find A Topic\",\"link\":\"/topics/lobbying\",\"data-clicky-href\":\"#widget/topics/find\",\"label\":\"lobbying\"},{\"data-clicky-title\":\"Widget: Find A Topic\",\"link\":\"/topics/lobbyists\",\"data-clicky-href\":\"#widget/topics/find\",\"label\":\"lobbyists\"},{\"data-clicky-title\":\"Widget: Find A Topic\",\"link\":\"/topics/london\",\"data-clicky-href\":\"#widget/topics/find\",\"label\":\"London\"},{\"data-clicky-title\":\"Widget: Find A Topic\",\"link\":\"/topics/lori_berenson\",\"data-clicky-href\":\"#widget/topics/find\",\"label\":\"Lori Berenson\"},{\"data-clicky-title\":\"Widget: Find A Topic\",\"link\":\"/topics/lou_dobbs\",\"data-clicky-href\":\"#widget/topics/find\",\"label\":\"Lou Dobbs\"},{\"data-clicky-title\":\"Widget: Find A Topic\",\"link\":\"/topics/lpfm\",\"data-clicky-href\":\"#widget/topics/find\",\"label\":\"LPFM\"},{\"data-clicky-title\":\"Widget: Find A Topic\",\"link\":\"/topics/luis_posada_carriles\",\"data-clicky-href\":\"#widget/topics/find\",\"label\":\"Luis Posada Carriles\"},{\"data-clicky-title\":\"Widget: Find A Topic\",\"link\":\"/topics/lynne_stewart\",\"data-clicky-href\":\"#widget/topics/find\",\"label\":\"Lynne Stewart\"},{\"data-clicky-title\":\"Widget: Find A Topic\",\"link\":\"/topics/malcolm_x\",\"data-clicky-href\":\"#widget/topics/find\",\"label\":\"Malcolm X\"},{\"data-clicky-title\":\"Widget: Find A Topic\",\"link\":\"/topics/maldives\",\"data-clicky-href\":\"#widget/topics/find\",\"label\":\"Maldives\"},{\"data-clicky-title\":\"Widget: Find A Topic\",\"link\":\"/topics/mali\",\"data-clicky-href\":\"#widget/topics/find\",\"label\":\"Mali\"},{\"data-clicky-title\":\"Widget: Find A Topic\",\"link\":\"/topics/manning_marable\",\"data-clicky-href\":\"#widget/topics/find\",\"label\":\"Manning Marable\"},{\"data-clicky-title\":\"Widget: Find A Topic\",\"link\":\"/topics/marijuana\",\"data-clicky-href\":\"#widget/topics/find\",\"label\":\"Marijuana\"},{\"data-clicky-title\":\"Widget: Find A Topic\",\"link\":\"/topics/marriage_equality\",\"data-clicky-href\":\"#widget/topics/find\",\"label\":\"marriage equality\"},{\"data-clicky-title\":\"Widget: Find A Topic\",\"link\":\"/topics/media_analysis\",\"data-clicky-href\":\"#widget/topics/find\",\"label\":\"Media Analysis\"},{\"data-clicky-title\":\"Widget: Find A Topic\",\"link\":\"/topics/media_anaylsis\",\"data-clicky-href\":\"#widget/topics/find\",\"label\":\"media anaylsis\"},{\"data-clicky-title\":\"Widget: Find A Topic\",\"link\":\"/topics/media_consolidation\",\"data-clicky-href\":\"#widget/topics/find\",\"label\":\"Media Consolidation\"},{\"data-clicky-title\":\"Widget: Find A Topic\",\"link\":\"/topics/media_policy\",\"data-clicky-href\":\"#widget/topics/find\",\"label\":\"Media Policy\"},{\"data-clicky-title\":\"Widget: Find A Topic\",\"link\":\"/topics/medicaid\",\"data-clicky-href\":\"#widget/topics/find\",\"label\":\"Medicaid\"},{\"data-clicky-title\":\"Widget: Find A Topic\",\"link\":\"/topics/medical_experimentation\",\"data-clicky-href\":\"#widget/topics/find\",\"label\":\"Medical Experimentation\"},{\"data-clicky-title\":\"Widget: Find A Topic\",\"link\":\"/topics/medicare\",\"data-clicky-href\":\"#widget/topics/find\",\"label\":\"Medicare\"},{\"data-clicky-title\":\"Widget: Find A Topic\",\"link\":\"/topics/mexico\",\"data-clicky-href\":\"#widget/topics/find\",\"label\":\"Mexico\"},{\"data-clicky-title\":\"Widget: Find A Topic\",\"link\":\"/topics/michael_moore\",\"data-clicky-href\":\"#widget/topics/find\",\"label\":\"Michael Moore\"},{\"data-clicky-title\":\"Widget: Find A Topic\",\"link\":\"/topics/michelle_bachmann\",\"data-clicky-href\":\"#widget/topics/find\",\"label\":\"Michele Bachmann\"},{\"data-clicky-title\":\"Widget: Find A Topic\",\"link\":\"/topics/michigan\",\"data-clicky-href\":\"#widget/topics/find\",\"label\":\"Michigan\"},{\"data-clicky-title\":\"Widget: Find A Topic\",\"link\":\"/topics/middle_class\",\"data-clicky-href\":\"#widget/topics/find\",\"label\":\"Middle Class\"},{\"data-clicky-title\":\"Widget: Find A Topic\",\"link\":\"/topics/middle_east\",\"data-clicky-href\":\"#widget/topics/find\",\"label\":\"Middle East\"},{\"data-clicky-title\":\"Widget: Find A Topic\",\"link\":\"/topics/military\",\"data-clicky-href\":\"#widget/topics/find\",\"label\":\"Military\"},{\"data-clicky-title\":\"Widget: Find A Topic\",\"link\":\"/topics/military_industrial_complex\",\"data-clicky-href\":\"#widget/topics/find\",\"label\":\"Military Industrial Complex\"},{\"data-clicky-title\":\"Widget: Find A Topic\",\"link\":\"/topics/military_industrial_complex\",\"data-clicky-href\":\"#widget/topics/find\",\"label\":\"Military-industrial complex\"},{\"data-clicky-title\":\"Widget: Find A Topic\",\"link\":\"/topics/minnesota\",\"data-clicky-href\":\"#widget/topics/find\",\"label\":\"Minnesota\"},{\"data-clicky-title\":\"Widget: Find A Topic\",\"link\":\"/topics/mississippi\",\"data-clicky-href\":\"#widget/topics/find\",\"label\":\"Mississippi\"},{\"data-clicky-title\":\"Widget: Find A Topic\",\"link\":\"/topics/mitt_romney\",\"data-clicky-href\":\"#widget/topics/find\",\"label\":\"Mitt Romney\"},{\"data-clicky-title\":\"Widget: Find A Topic\",\"link\":\"/topics/money_politics\",\"data-clicky-href\":\"#widget/topics/find\",\"label\":\"Money &amp; Politics\"},{\"data-clicky-title\":\"Widget: Find A Topic\",\"link\":\"/topics/monsanto\",\"data-clicky-href\":\"#widget/topics/find\",\"label\":\"Monsanto\"},{\"data-clicky-title\":\"Widget: Find A Topic\",\"link\":\"/topics/mountaintop_removal\",\"data-clicky-href\":\"#widget/topics/find\",\"label\":\"Mountaintop Removal\"},{\"data-clicky-title\":\"Widget: Find A Topic\",\"link\":\"/topics/muammar_gaddafi\",\"data-clicky-href\":\"#widget/topics/find\",\"label\":\"Muammar Gaddafi\"},{\"data-clicky-title\":\"Widget: Find A Topic\",\"link\":\"/topics/mubarak\",\"data-clicky-href\":\"#widget/topics/find\",\"label\":\"Mubarak\"},{\"data-clicky-title\":\"Widget: Find A Topic\",\"link\":\"/topics/mumia_abu_jamal\",\"data-clicky-href\":\"#widget/topics/find\",\"label\":\"Mumia Abu-Jamal\"},{\"data-clicky-title\":\"Widget: Find A Topic\",\"link\":\"/topics/murdoch_media_scandal\",\"data-clicky-href\":\"#widget/topics/find\",\"label\":\"Murdoch Media Scandal\"},{\"data-clicky-title\":\"Widget: Find A Topic\",\"link\":\"/topics/muslim\",\"data-clicky-href\":\"#widget/topics/find\",\"label\":\"Muslim\"},{\"data-clicky-title\":\"Widget: Find A Topic\",\"link\":\"/topics/nagasaki\",\"data-clicky-href\":\"#widget/topics/find\",\"label\":\"Nagasaki\"},{\"data-clicky-title\":\"Widget: Find A Topic\",\"link\":\"/topics/naomi_klein\",\"data-clicky-href\":\"#widget/topics/find\",\"label\":\"Naomi Klein\"},{\"data-clicky-title\":\"Widget: Find A Topic\",\"link\":\"/topics/national_conference_for_media_reform\",\"data-clicky-href\":\"#widget/topics/find\",\"label\":\"National Conference for Media Reform\"},{\"data-clicky-title\":\"Widget: Find A Topic\",\"link\":\"/topics/native_american\",\"data-clicky-href\":\"#widget/topics/find\",\"label\":\"Native American\"},{\"data-clicky-title\":\"Widget: Find A Topic\",\"link\":\"/topics/nato\",\"data-clicky-href\":\"#widget/topics/find\",\"label\":\"NATO\"},{\"data-clicky-title\":\"Widget: Find A Topic\",\"link\":\"/topics/natural_gas_and_oil\",\"data-clicky-href\":\"#widget/topics/find\",\"label\":\"Natural Gas &amp; Oil Drilling\"},{\"data-clicky-title\":\"Widget: Find A Topic\",\"link\":\"/topics/ndaa\",\"data-clicky-href\":\"#widget/topics/find\",\"label\":\"NDAA\"},{\"data-clicky-title\":\"Widget: Find A Topic\",\"link\":\"/topics/new_jersey\",\"data-clicky-href\":\"#widget/topics/find\",\"label\":\"New Jersey\"},{\"data-clicky-title\":\"Widget: Find A Topic\",\"link\":\"/topics/new_mexico\",\"data-clicky-href\":\"#widget/topics/find\",\"label\":\"New Mexico\"},{\"data-clicky-title\":\"Widget: Find A Topic\",\"link\":\"/topics/new_orleans\",\"data-clicky-href\":\"#widget/topics/find\",\"label\":\"New Orleans\"},{\"data-clicky-title\":\"Widget: Find A Topic\",\"link\":\"/topics/new_york\",\"data-clicky-href\":\"#widget/topics/find\",\"label\":\"New York\"},{\"data-clicky-title\":\"Widget: Find A Topic\",\"link\":\"/topics/newtown_shooting\",\"data-clicky-href\":\"#widget/topics/find\",\"label\":\"Newtown Shooting\"},{\"data-clicky-title\":\"Widget: Find A Topic\",\"link\":\"/topics/nigeria\",\"data-clicky-href\":\"#widget/topics/find\",\"label\":\"Nigeria\"},{\"data-clicky-title\":\"Widget: Find A Topic\",\"link\":\"/topics/no_child_left_behind\",\"data-clicky-href\":\"#widget/topics/find\",\"label\":\"No Child Left Behind\"},{\"data-clicky-title\":\"Widget: Find A Topic\",\"link\":\"/topics/noam_chomsky\",\"data-clicky-href\":\"#widget/topics/find\",\"label\":\"Noam Chomsky\"},{\"data-clicky-title\":\"Widget: Find A Topic\",\"link\":\"/topics/nobel_peace_prize\",\"data-clicky-href\":\"#widget/topics/find\",\"label\":\"Nobel Peace Prize\"},{\"data-clicky-title\":\"Widget: Find A Topic\",\"link\":\"/topics/north_carolina\",\"data-clicky-href\":\"#widget/topics/find\",\"label\":\"North Carolina\"},{\"data-clicky-title\":\"Widget: Find A Topic\",\"link\":\"/topics/north_korea\",\"data-clicky-href\":\"#widget/topics/find\",\"label\":\"North Korea\"},{\"data-clicky-title\":\"Widget: Find A Topic\",\"link\":\"/topics/norway\",\"data-clicky-href\":\"#widget/topics/find\",\"label\":\"Norway\"},{\"data-clicky-title\":\"Widget: Find A Topic\",\"link\":\"/topics/nsa\",\"data-clicky-href\":\"#widget/topics/find\",\"label\":\"NSA\"},{\"data-clicky-title\":\"Widget: Find A Topic\",\"link\":\"/topics/nuclear_power\",\"data-clicky-href\":\"#widget/topics/find\",\"label\":\"Nuclear Power\"},{\"data-clicky-title\":\"Widget: Find A Topic\",\"link\":\"/topics/nypd_muslim_spy_program\",\"data-clicky-href\":\"#widget/topics/find\",\"label\":\"NYPD Muslim Spy Program\"},{\"data-clicky-title\":\"Widget: Find A Topic\",\"link\":\"/topics/obama\",\"data-clicky-href\":\"#widget/topics/find\",\"label\":\"Obama\"},{\"data-clicky-title\":\"Widget: Find A Topic\",\"link\":\"/topics/occupy_wall_street\",\"data-clicky-href\":\"#widget/topics/find\",\"label\":\"Occupy Wall Street\"},{\"data-clicky-title\":\"Widget: Find A Topic\",\"link\":\"/topics/ocean\",\"data-clicky-href\":\"#widget/topics/find\",\"label\":\"Ocean\"},{\"data-clicky-title\":\"Widget: Find A Topic\",\"link\":\"/topics/offshore_drilling\",\"data-clicky-href\":\"#widget/topics/find\",\"label\":\"Offshore Drilling\"},{\"data-clicky-title\":\"Widget: Find A Topic\",\"link\":\"/topics/ohio\",\"data-clicky-href\":\"#widget/topics/find\",\"label\":\"Ohio\"},{\"data-clicky-title\":\"Widget: Find A Topic\",\"link\":\"/topics/olympics\",\"data-clicky-href\":\"#widget/topics/find\",\"label\":\"Olympics\"},{\"data-clicky-title\":\"Widget: Find A Topic\",\"link\":\"/topics/open_source\",\"data-clicky-href\":\"#widget/topics/find\",\"label\":\"Open Source\"},{\"data-clicky-title\":\"Widget: Find A Topic\",\"link\":\"/topics/osama_bin_laden\",\"data-clicky-href\":\"#widget/topics/find\",\"label\":\"Osama bin Laden\"},{\"data-clicky-title\":\"Widget: Find A Topic\",\"link\":\"/topics/oscars_2010\",\"data-clicky-href\":\"#widget/topics/find\",\"label\":\"Oscars\"},{\"data-clicky-title\":\"Widget: Find A Topic\",\"link\":\"/topics/osha\",\"data-clicky-href\":\"#widget/topics/find\",\"label\":\"OSHA\"},{\"data-clicky-title\":\"Widget: Find A Topic\",\"link\":\"/topics/pakistan\",\"data-clicky-href\":\"#widget/topics/find\",\"label\":\"Pakistan\"},{\"data-clicky-title\":\"Widget: Find A Topic\",\"link\":\"/topics/palestine\",\"data-clicky-href\":\"#widget/topics/find\",\"label\":\"Palestine\"},{\"data-clicky-title\":\"Widget: Find A Topic\",\"link\":\"/topics/paul_ryan\",\"data-clicky-href\":\"#widget/topics/find\",\"label\":\"Paul Ryan\"},{\"data-clicky-title\":\"Widget: Find A Topic\",\"link\":\"/topics/peace\",\"data-clicky-href\":\"#widget/topics/find\",\"label\":\"Peace\"},{\"data-clicky-title\":\"Widget: Find A Topic\",\"link\":\"/topics/peru\",\"data-clicky-href\":\"#widget/topics/find\",\"label\":\"Peru\"},{\"data-clicky-title\":\"Widget: Find A Topic\",\"link\":\"/topics/philippines\",\"data-clicky-href\":\"#widget/topics/find\",\"label\":\"Philippines\"},{\"data-clicky-title\":\"Widget: Find A Topic\",\"link\":\"/topics/pipeline\",\"data-clicky-href\":\"#widget/topics/find\",\"label\":\"Pipeline\"},{\"data-clicky-title\":\"Widget: Find A Topic\",\"link\":\"/topics/police\",\"data-clicky-href\":\"#widget/topics/find\",\"label\":\"Police\"},{\"data-clicky-title\":\"Widget: Find A Topic\",\"link\":\"/topics/police_brutality\",\"data-clicky-href\":\"#widget/topics/find\",\"label\":\"Police brutality\"},{\"data-clicky-title\":\"Widget: Find A Topic\",\"link\":\"/topics/poor\",\"data-clicky-href\":\"#widget/topics/find\",\"label\":\"poor\"},{\"data-clicky-title\":\"Widget: Find A Topic\",\"link\":\"/topics/poverty\",\"data-clicky-href\":\"#widget/topics/find\",\"label\":\"Poverty\"},{\"data-clicky-title\":\"Widget: Find A Topic\",\"link\":\"/topics/pr_industry\",\"data-clicky-href\":\"#widget/topics/find\",\"label\":\"PR Industry\"},{\"data-clicky-title\":\"Widget: Find A Topic\",\"link\":\"/topics/prison\",\"data-clicky-href\":\"#widget/topics/find\",\"label\":\"prison\"},{\"data-clicky-title\":\"Widget: Find A Topic\",\"link\":\"/topics/private_contractors\",\"data-clicky-href\":\"#widget/topics/find\",\"label\":\"Private Contractors\"},{\"data-clicky-title\":\"Widget: Find A Topic\",\"link\":\"/topics/privatization\",\"data-clicky-href\":\"#widget/topics/find\",\"label\":\"privatization\"},{\"data-clicky-title\":\"Widget: Find A Topic\",\"link\":\"/topics/protests\",\"data-clicky-href\":\"#widget/topics/find\",\"label\":\"Protests\"},{\"data-clicky-title\":\"Widget: Find A Topic\",\"link\":\"/topics/psychology_and_justice\",\"data-clicky-href\":\"#widget/topics/find\",\"label\":\"Psychology and Justice\"},{\"data-clicky-title\":\"Widget: Find A Topic\",\"link\":\"/topics/ptsd\",\"data-clicky-href\":\"#widget/topics/find\",\"label\":\"PTSD\"},{\"data-clicky-title\":\"Widget: Find A Topic\",\"link\":\"/topics/puerto_rico\",\"data-clicky-href\":\"#widget/topics/find\",\"label\":\"Puerto Rico\"},{\"data-clicky-title\":\"Widget: Find A Topic\",\"link\":\"/topics/pussy_riot\",\"data-clicky-href\":\"#widget/topics/find\",\"label\":\"Pussy Riot\"},{\"data-clicky-title\":\"Widget: Find A Topic\",\"link\":\"/topics/race_in_america\",\"data-clicky-href\":\"#widget/topics/find\",\"label\":\"Race in America\"},{\"data-clicky-title\":\"Widget: Find A Topic\",\"link\":\"/topics/rachel_corrie\",\"data-clicky-href\":\"#widget/topics/find\",\"label\":\"Rachel Corrie\"},{\"data-clicky-title\":\"Widget: Find A Topic\",\"link\":\"/topics/racism\",\"data-clicky-href\":\"#widget/topics/find\",\"label\":\"Racism\"},{\"data-clicky-title\":\"Widget: Find A Topic\",\"link\":\"/topics/rape\",\"data-clicky-href\":\"#widget/topics/find\",\"label\":\"Rape\"},{\"data-clicky-title\":\"Widget: Find A Topic\",\"link\":\"/topics/red_cross\",\"data-clicky-href\":\"#widget/topics/find\",\"label\":\"Red Cross\"},{\"data-clicky-title\":\"Widget: Find A Topic\",\"link\":\"/topics/regulation\",\"data-clicky-href\":\"#widget/topics/find\",\"label\":\"Regulation\"},{\"data-clicky-title\":\"Widget: Find A Topic\",\"link\":\"/topics/republican\",\"data-clicky-href\":\"#widget/topics/find\",\"label\":\"Republican\"},{\"data-clicky-title\":\"Widget: Find A Topic\",\"link\":\"/topics/republican_party\",\"data-clicky-href\":\"#widget/topics/find\",\"label\":\"Republican Party\"},{\"data-clicky-title\":\"Widget: Find A Topic\",\"link\":\"/topics/rick_perry\",\"data-clicky-href\":\"#widget/topics/find\",\"label\":\"Rick Perry\"},{\"data-clicky-title\":\"Widget: Find A Topic\",\"link\":\"/topics/right_livelihood_award\",\"data-clicky-href\":\"#widget/topics/find\",\"label\":\"Right Livelihood Award\"},{\"data-clicky-title\":\"Widget: Find A Topic\",\"link\":\"/topics/right_wing_militias\",\"data-clicky-href\":\"#widget/topics/find\",\"label\":\"right-wing militias\"},{\"data-clicky-title\":\"Widget: Find A Topic\",\"link\":\"/topics/rio_20\",\"data-clicky-href\":\"#widget/topics/find\",\"label\":\"Rio+20\"},{\"data-clicky-title\":\"Widget: Find A Topic\",\"link\":\"/topics/rnc_2008\",\"data-clicky-href\":\"#widget/topics/find\",\"label\":\"RNC 2008\"},{\"data-clicky-title\":\"Widget: Find A Topic\",\"link\":\"/topics/rnc_2012\",\"data-clicky-href\":\"#widget/topics/find\",\"label\":\"RNC 2012\"},{\"data-clicky-title\":\"Widget: Find A Topic\",\"link\":\"/topics/robert_redford\",\"data-clicky-href\":\"#widget/topics/find\",\"label\":\"Robert Redford\"},{\"data-clicky-title\":\"Widget: Find A Topic\",\"link\":\"/topics/rolling_rebellions\",\"data-clicky-href\":\"#widget/topics/find\",\"label\":\"Rolling Rebellions\"},{\"data-clicky-title\":\"Widget: Find A Topic\",\"link\":\"/topics/russia\",\"data-clicky-href\":\"#widget/topics/find\",\"label\":\"Russia\"},{\"data-clicky-title\":\"Widget: Find A Topic\",\"link\":\"/topics/rwanda\",\"data-clicky-href\":\"#widget/topics/find\",\"label\":\"Rwanda\"},{\"data-clicky-title\":\"Widget: Find A Topic\",\"link\":\"/topics/saudi_arabia\",\"data-clicky-href\":\"#widget/topics/find\",\"label\":\"Saudi Arabia\"},{\"data-clicky-title\":\"Widget: Find A Topic\",\"link\":\"/topics/school_of_the_americas\",\"data-clicky-href\":\"#widget/topics/find\",\"label\":\"School of the Americas\"},{\"data-clicky-title\":\"Widget: Find A Topic\",\"link\":\"/topics/sec\",\"data-clicky-href\":\"#widget/topics/find\",\"label\":\"SEC\"},{\"data-clicky-title\":\"Widget: Find A Topic\",\"link\":\"/topics/secure_communities\",\"data-clicky-href\":\"#widget/topics/find\",\"label\":\"Secure Communities\"},{\"data-clicky-title\":\"Widget: Find A Topic\",\"link\":\"/topics/september_11\",\"data-clicky-href\":\"#widget/topics/find\",\"label\":\"September 11\"},{\"data-clicky-title\":\"Widget: Find A Topic\",\"link\":\"/topics/sex_workers\",\"data-clicky-href\":\"#widget/topics/find\",\"label\":\"sex workers\"},{\"data-clicky-title\":\"Widget: Find A Topic\",\"link\":\"/topics/sexual_assault\",\"data-clicky-href\":\"#widget/topics/find\",\"label\":\"Sexual Assault\"},{\"data-clicky-title\":\"Widget: Find A Topic\",\"link\":\"/topics/sharif_kouddous\",\"data-clicky-href\":\"#widget/topics/find\",\"label\":\"Sharif Abdel Kouddous\"},{\"data-clicky-title\":\"Widget: Find A Topic\",\"link\":\"/topics/shirley_sherrod\",\"data-clicky-href\":\"#widget/topics/find\",\"label\":\"Shirley Sherrod\"},{\"data-clicky-title\":\"Widget: Find A Topic\",\"link\":\"/topics/sikh\",\"data-clicky-href\":\"#widget/topics/find\",\"label\":\"Sikh\"},{\"data-clicky-title\":\"Widget: Find A Topic\",\"link\":\"/topics/social_media\",\"data-clicky-href\":\"#widget/topics/find\",\"label\":\"Social media\"},{\"data-clicky-title\":\"Widget: Find A Topic\",\"link\":\"/topics/social_security\",\"data-clicky-href\":\"#widget/topics/find\",\"label\":\"Social Security\"},{\"data-clicky-title\":\"Widget: Find A Topic\",\"link\":\"/topics/soldier_suicides\",\"data-clicky-href\":\"#widget/topics/find\",\"label\":\"Soldier Suicides\"},{\"data-clicky-title\":\"Widget: Find A Topic\",\"link\":\"/topics/solitary_confinement\",\"data-clicky-href\":\"#widget/topics/find\",\"label\":\"solitary confinement\"},{\"data-clicky-title\":\"Widget: Find A Topic\",\"link\":\"/topics/somalia\",\"data-clicky-href\":\"#widget/topics/find\",\"label\":\"Somalia\"},{\"data-clicky-title\":\"Widget: Find A Topic\",\"link\":\"/topics/south_africa\",\"data-clicky-href\":\"#widget/topics/find\",\"label\":\"South Africa\"},{\"data-clicky-title\":\"Widget: Find A Topic\",\"link\":\"/topics/south_korea\",\"data-clicky-href\":\"#widget/topics/find\",\"label\":\"South Korea\"},{\"data-clicky-title\":\"Widget: Find A Topic\",\"link\":\"/topics/spain\",\"data-clicky-href\":\"#widget/topics/find\",\"label\":\"Spain\"},{\"data-clicky-title\":\"Widget: Find A Topic\",\"link\":\"/topics/sports\",\"data-clicky-href\":\"#widget/topics/find\",\"label\":\"Sports &amp; Politics\"},{\"data-clicky-title\":\"Widget: Find A Topic\",\"link\":\"/topics/state_of_the_union\",\"data-clicky-href\":\"#widget/topics/find\",\"label\":\"State of the Union\"},{\"data-clicky-title\":\"Widget: Find A Topic\",\"link\":\"/topics/steubenville\",\"data-clicky-href\":\"#widget/topics/find\",\"label\":\"Steubenville\"},{\"data-clicky-title\":\"Widget: Find A Topic\",\"link\":\"/topics/stop_frisk\",\"data-clicky-href\":\"#widget/topics/find\",\"label\":\"Stop and Frisk\"},{\"data-clicky-title\":\"Widget: Find A Topic\",\"link\":\"/topics/students\",\"data-clicky-href\":\"#widget/topics/find\",\"label\":\"Students\"},{\"data-clicky-title\":\"Widget: Find A Topic\",\"link\":\"/topics/sudan\",\"data-clicky-href\":\"#widget/topics/find\",\"label\":\"Sudan\"},{\"data-clicky-title\":\"Widget: Find A Topic\",\"link\":\"/topics/sundance_film_festival\",\"data-clicky-href\":\"#widget/topics/find\",\"label\":\"Sundance Film Festival\"},{\"data-clicky-title\":\"Widget: Find A Topic\",\"link\":\"/topics/supreme_court\",\"data-clicky-href\":\"#widget/topics/find\",\"label\":\"Supreme Court\"},{\"data-clicky-title\":\"Widget: Find A Topic\",\"link\":\"/topics/syria\",\"data-clicky-href\":\"#widget/topics/find\",\"label\":\"Syria\"},{\"data-clicky-title\":\"Widget: Find A Topic\",\"link\":\"/topics/tar_sands\",\"data-clicky-href\":\"#widget/topics/find\",\"label\":\"Tar Sands\"},{\"data-clicky-title\":\"Widget: Find A Topic\",\"link\":\"/topics/tax_havens\",\"data-clicky-href\":\"#widget/topics/find\",\"label\":\"Tax Havens\"},{\"data-clicky-title\":\"Widget: Find A Topic\",\"link\":\"/topics/tax_protest\",\"data-clicky-href\":\"#widget/topics/find\",\"label\":\"Tax Protest\"},{\"data-clicky-title\":\"Widget: Find A Topic\",\"link\":\"/topics/tax_reform\",\"data-clicky-href\":\"#widget/topics/find\",\"label\":\"tax reform\"},{\"data-clicky-title\":\"Widget: Find A Topic\",\"link\":\"/topics/taxes\",\"data-clicky-href\":\"#widget/topics/find\",\"label\":\"Taxes\"},{\"data-clicky-title\":\"Widget: Find A Topic\",\"link\":\"/topics/tea_party\",\"data-clicky-href\":\"#widget/topics/find\",\"label\":\"Tea Party\"},{\"data-clicky-title\":\"Widget: Find A Topic\",\"link\":\"/topics/telecommunications\",\"data-clicky-href\":\"#widget/topics/find\",\"label\":\"Telecommunications\"},{\"data-clicky-title\":\"Widget: Find A Topic\",\"link\":\"/topics/texas\",\"data-clicky-href\":\"#widget/topics/find\",\"label\":\"Texas\"},{\"data-clicky-title\":\"Widget: Find A Topic\",\"link\":\"/topics/thailand\",\"data-clicky-href\":\"#widget/topics/find\",\"label\":\"Thailand\"},{\"data-clicky-title\":\"Widget: Find A Topic\",\"link\":\"/topics/tibet\",\"data-clicky-href\":\"#widget/topics/find\",\"label\":\"Tibet\"},{\"data-clicky-title\":\"Widget: Find A Topic\",\"link\":\"/topics/torture\",\"data-clicky-href\":\"#widget/topics/find\",\"label\":\"Torture\"},{\"data-clicky-title\":\"Widget: Find A Topic\",\"link\":\"/topics/trayvon_martin\",\"data-clicky-href\":\"#widget/topics/find\",\"label\":\"Trayvon Martin\"},{\"data-clicky-title\":\"Widget: Find A Topic\",\"link\":\"/topics/troy_davis\",\"data-clicky-href\":\"#widget/topics/find\",\"label\":\"Troy Davis\"},{\"data-clicky-title\":\"Widget: Find A Topic\",\"link\":\"/topics/tuition\",\"data-clicky-href\":\"#widget/topics/find\",\"label\":\"Tuition\"},{\"data-clicky-title\":\"Widget: Find A Topic\",\"link\":\"/topics/tunisia\",\"data-clicky-href\":\"#widget/topics/find\",\"label\":\"Tunisia\"},{\"data-clicky-title\":\"Widget: Find A Topic\",\"link\":\"/topics/turkey\",\"data-clicky-href\":\"#widget/topics/find\",\"label\":\"Turkey\"},{\"data-clicky-title\":\"Widget: Find A Topic\",\"link\":\"/topics/us_economy\",\"data-clicky-href\":\"#widget/topics/find\",\"label\":\"U.S. Economy\"},{\"data-clicky-title\":\"Widget: Find A Topic\",\"link\":\"/topics/us_hikers\",\"data-clicky-href\":\"#widget/topics/find\",\"label\":\"U.S. Hikers Freed from Iran\"},{\"data-clicky-title\":\"Widget: Find A Topic\",\"link\":\"/topics/us_labor_protests\",\"data-clicky-href\":\"#widget/topics/find\",\"label\":\"U.S. Labor Protests\"},{\"data-clicky-title\":\"Widget: Find A Topic\",\"link\":\"/topics/us_social_forum\",\"data-clicky-href\":\"#widget/topics/find\",\"label\":\"U.S. Social Forum\"},{\"data-clicky-title\":\"Widget: Find A Topic\",\"link\":\"/topics/uganda\",\"data-clicky-href\":\"#widget/topics/find\",\"label\":\"Uganda\"},{\"data-clicky-title\":\"Widget: Find A Topic\",\"link\":\"/topics/undocumented\",\"data-clicky-href\":\"#widget/topics/find\",\"label\":\"Undocumented\"},{\"data-clicky-title\":\"Widget: Find A Topic\",\"link\":\"/topics/unemployment\",\"data-clicky-href\":\"#widget/topics/find\",\"label\":\"unemployment\"},{\"data-clicky-title\":\"Widget: Find A Topic\",\"link\":\"/topics/unions\",\"data-clicky-href\":\"#widget/topics/find\",\"label\":\"Unions\"},{\"data-clicky-title\":\"Widget: Find A Topic\",\"link\":\"/topics/united_nations\",\"data-clicky-href\":\"#widget/topics/find\",\"label\":\"United Nations\"},{\"data-clicky-title\":\"Widget: Find A Topic\",\"link\":\"/topics/uranium\",\"data-clicky-href\":\"#widget/topics/find\",\"label\":\"uranium\"},{\"data-clicky-title\":\"Widget: Find A Topic\",\"link\":\"/topics/uraguay\",\"data-clicky-href\":\"#widget/topics/find\",\"label\":\"Uruguay\"},{\"data-clicky-title\":\"Widget: Find A Topic\",\"link\":\"/topics/usa_patriot_act\",\"data-clicky-href\":\"#widget/topics/find\",\"label\":\"USA PATRIOT Act\"},{\"data-clicky-title\":\"Widget: Find A Topic\",\"link\":\"/topics/usps\",\"data-clicky-href\":\"#widget/topics/find\",\"label\":\"USPS\"},{\"data-clicky-title\":\"Widget: Find A Topic\",\"link\":\"/topics/utah\",\"data-clicky-href\":\"#widget/topics/find\",\"label\":\"utah\"},{\"data-clicky-title\":\"Widget: Find A Topic\",\"link\":\"/topics/venezuela\",\"data-clicky-href\":\"#widget/topics/find\",\"label\":\"Venezuela\"},{\"data-clicky-title\":\"Widget: Find A Topic\",\"link\":\"/topics/verizon\",\"data-clicky-href\":\"#widget/topics/find\",\"label\":\"Verizon\"},{\"data-clicky-title\":\"Widget: Find A Topic\",\"link\":\"/topics/vermont\",\"data-clicky-href\":\"#widget/topics/find\",\"label\":\"Vermont\"},{\"data-clicky-title\":\"Widget: Find A Topic\",\"link\":\"/topics/veterans\",\"data-clicky-href\":\"#widget/topics/find\",\"label\":\"Veterans\"},{\"data-clicky-title\":\"Widget: Find A Topic\",\"link\":\"/topics/voting\",\"data-clicky-href\":\"#widget/topics/find\",\"label\":\"Voting\"},{\"data-clicky-title\":\"Widget: Find A Topic\",\"link\":\"/topics/wall_street\",\"data-clicky-href\":\"#widget/topics/find\",\"label\":\"Wall Street\"},{\"data-clicky-title\":\"Widget: Find A Topic\",\"link\":\"/topics/walmart\",\"data-clicky-href\":\"#widget/topics/find\",\"label\":\"Walmart\"},{\"data-clicky-title\":\"Widget: Find A Topic\",\"link\":\"/topics/wangari_maathai\",\"data-clicky-href\":\"#widget/topics/find\",\"label\":\"Wangari Maathai\"},{\"data-clicky-title\":\"Widget: Find A Topic\",\"link\":\"/topics/war\",\"data-clicky-href\":\"#widget/topics/find\",\"label\":\"War\"},{\"data-clicky-title\":\"Widget: Find A Topic\",\"link\":\"/topics/war_on_terror\",\"data-clicky-href\":\"#widget/topics/find\",\"label\":\"War on Terror\"},{\"data-clicky-title\":\"Widget: Find A Topic\",\"link\":\"/topics/water\",\"data-clicky-href\":\"#widget/topics/find\",\"label\":\"water\"},{\"data-clicky-title\":\"Widget: Find A Topic\",\"link\":\"/topics/west_memphis_three\",\"data-clicky-href\":\"#widget/topics/find\",\"label\":\"West Memphis Three\"},{\"data-clicky-title\":\"Widget: Find A Topic\",\"link\":\"/topics/western_sahara\",\"data-clicky-href\":\"#widget/topics/find\",\"label\":\"Western Sahara\"},{\"data-clicky-title\":\"Widget: Find A Topic\",\"link\":\"/topics/whistleblowers\",\"data-clicky-href\":\"#widget/topics/find\",\"label\":\"Whistleblowers\"},{\"data-clicky-title\":\"Widget: Find A Topic\",\"link\":\"/topics/white_power\",\"data-clicky-href\":\"#widget/topics/find\",\"label\":\"White power\"},{\"data-clicky-title\":\"Widget: Find A Topic\",\"link\":\"/topics/wikileaks\",\"data-clicky-href\":\"#widget/topics/find\",\"label\":\"Wikileaks\"},{\"data-clicky-title\":\"Widget: Find A Topic\",\"link\":\"/topics/wiretapping\",\"data-clicky-href\":\"#widget/topics/find\",\"label\":\"Wiretapping\"},{\"data-clicky-title\":\"Widget: Find A Topic\",\"link\":\"/topics/wisconsin\",\"data-clicky-href\":\"#widget/topics/find\",\"label\":\"Wisconsin\"},{\"data-clicky-title\":\"Widget: Find A Topic\",\"link\":\"/topics/wisconsin_sikh_temple_shooting\",\"data-clicky-href\":\"#widget/topics/find\",\"label\":\"Wisconsin Sikh Temple Shooting\"},{\"data-clicky-title\":\"Widget: Find A Topic\",\"link\":\"/topics/womens_health\",\"data-clicky-href\":\"#widget/topics/find\",\"label\":\"Women's Health\"},{\"data-clicky-title\":\"Widget: Find A Topic\",\"link\":\"/topics/womens_rights\",\"data-clicky-href\":\"#widget/topics/find\",\"label\":\"Women's Rights \"},{\"data-clicky-title\":\"Widget: Find A Topic\",\"link\":\"/topics/womens_rights\",\"data-clicky-href\":\"#widget/topics/find\",\"label\":\"Women\\u2019s Rights\"},{\"data-clicky-title\":\"Widget: Find A Topic\",\"link\":\"/topics/working_class\",\"data-clicky-href\":\"#widget/topics/find\",\"label\":\"Working Class\"},{\"data-clicky-title\":\"Widget: Find A Topic\",\"link\":\"/topics/world_peoples_summit_on_climate_change\",\"data-clicky-href\":\"#widget/topics/find\",\"label\":\"World Peoples' Summit on Climate Change\"},{\"data-clicky-title\":\"Widget: Find A Topic\",\"link\":\"/topics/wto\",\"data-clicky-href\":\"#widget/topics/find\",\"label\":\"WTO\"},{\"data-clicky-title\":\"Widget: Find A Topic\",\"link\":\"/topics/yemen\",\"data-clicky-href\":\"#widget/topics/find\",\"label\":\"Yemen\"}]\n</p>\n    </div>\n    \n  </div>",
    "date_published": null,
    "dek": null,
    "lead_image_url": "http://www.democracynow.org/images/dn-logo-for-podcast.png?3_0",
    "title": "Cooper Union Students Continue Tuition Protest",
    "rendered_pages": 1
}